django_colorhash/templatetags/colorhash.py
django_colorhash-0.1.0.dist-info/METADATA
django_colorhash-0.1.0.dist-info/WHEEL
django_colorhash-0.1.0.dist-info/top_level.txt
django_colorhash-0.1.0.dist-info/RECORD
