Metadata-Version: 2.2
Name: django-colorhash
Version: 0.1.0
Summary: color-hash templatetag for Django
Requires-Python: >=3.12
Requires-Dist: colorhash>=2.0.0
Requires-Dist: django>=4.2
